fretboard/__init__.py
fretboard/chord.py
fretboard/compat.py
fretboard/fretboard.py
fretboard/utils.py
fretboard-1.0.0.dist-info/DESCRIPTION.rst
fretboard-1.0.0.dist-info/METADATA
fretboard-1.0.0.dist-info/RECORD
fretboard-1.0.0.dist-info/WHEEL
fretboard-1.0.0.dist-info/metadata.json
fretboard-1.0.0.dist-info/top_level.txt
