Metadata-Version: 2.0
Name: fretboard
Version: 1.0.0
Summary: Fretboard is a python library for generating SVG fretboard images and chord charts in Python.
Home-page: https://github.com/dmpayton/python-fretboard
Author: Derek Payton
Author-email: derek.payton@gmail.com
License: MIT
Download-URL: https://github.com/dmpayton/python-fretboard/tarball/v1.0.0
Keywords: guitar fretboard chord
Platform: UNKNOWN
Classifier: Development Status :: 4 - Beta
Classifier: Intended Audience :: Developers
Classifier: License :: OSI Approved :: MIT License
Classifier: Programming Language :: Python
Classifier: Programming Language :: Python :: 2
Classifier: Programming Language :: Python :: 3
Requires-Dist: attrdict (==2.0.0)
Requires-Dist: svgwrite (==1.1.9)
Requires-Dist: PyYAML (==3.12)
